{
  "id": "ai-risk-assessment",
  "last_modified": "0001-01-01T00:00:00Z",
  "name": "AI Model Risk Assessment Completed",
  "description": "Ensures risk assessments are completed for all AI models before deployment (ISO 42001)",
  "effect": "forbid",
  "principal": "",
  "action": "",
  "resource": "ai_models",
  "conditions": [
    "exists_path(resource, \"deployment_date\")",
    "(!exists_path(resource, \"risk_assessment_date\")) || (cmp_gt(path(resource, \"risk_assessment_date\"), path(resource, \"deployment_date\")))"
  ],
  "condition_format": "cel",
  "severity": "high",
  "tags": [
    "ai",
    "ml",
    "risk",
    "assessment",
    "iso42001"
  ],
  "remediation": "Complete risk assessment for all AI models before deployment. Document potential harms, biases, and mitigation strategies.",
  "frameworks": [
    {
      "name": "ISO 42001",
      "controls": [
        "6.1",
        "6.2"
      ]
    },
    {
      "name": "SOC 2",
      "controls": [
        "CC3.2"
      ]
    }
  ]
}
