{
  "id": "aws-sagemaker-training-unencrypted",
  "last_modified": "0001-01-01T00:00:00Z",
  "name": "SageMaker Training Job Unencrypted Storage",
  "description": "SageMaker training job does not encrypt output data",
  "effect": "forbid",
  "principal": "",
  "action": "",
  "resource": "aws::sagemaker::training_job",
  "conditions": [
    "cmp_eq(path(resource, \"output_data_config.kms_key_id\"), null)"
  ],
  "condition_format": "cel",
  "severity": "high",
  "tags": [
    "ai",
    "sagemaker",
    "encryption",
    "training-data"
  ],
  "remediation": "Configure KMS encryption for training job output data.",
  "risk_categories": [
    "UNPROTECTED_DATA"
  ],
  "frameworks": [
    {
      "name": "NIST 800-53 r5",
      "controls": [
        "SC-12",
        "SC-13",
        "SC-28"
      ]
    },
    {
      "name": "PCI DSS v4.0.1",
      "controls": [
        "3.5",
        "4.2"
      ]
    },
    {
      "name": "CIS Controls v8",
      "controls": [
        "3"
      ]
    }
  ],
  "mitre_attack": [
    {
      "tactic": "Collection",
      "technique": "T1530"
    }
  ]
}
